farmdrop/__init__.py
farmdrop/celery.py
farmdrop/manage_farmdrop.py
farmdrop/settings.py
farmdrop/urls.py
farmdrop/wsgi.py
farmdrop/apps/__init__.py
farmdrop/frozen_deps/__init__.py
farmdrop/static/css/all.css
farmdrop/static/css/dashboard.css
farmdrop/static/css/dashboard.css.map
farmdrop/static/css/dashboard.min.css
farmdrop/static/css/dashboard.min.css.gz
farmdrop/static/css/storefront.css
farmdrop/static/css/storefront.css.map
farmdrop/static/css/storefront.min.css
farmdrop/static/css/storefront.min.css.gz
farmdrop/static/fonts/2C8496_1_0.eot
farmdrop/static/fonts/2C8496_1_0.ttf
farmdrop/static/fonts/2C8496_1_0.woff
farmdrop/static/fonts/2C8496_1_0.woff2
farmdrop/static/fonts/FontAwesome.otf
farmdrop/static/fonts/LICENSE.txt
farmdrop/static/fonts/Material-Design-Icons.eot
farmdrop/static/fonts/Material-Design-Icons.svg
farmdrop/static/fonts/Material-Design-Icons.ttf
farmdrop/static/fonts/Material-Design-Icons.woff
farmdrop/static/fonts/Material-Design-Icons.woff2
farmdrop/static/fonts/Roboto-Bold.eot
farmdrop/static/fonts/Roboto-Bold.ttf
farmdrop/static/fonts/Roboto-Bold.woff
farmdrop/static/fonts/Roboto-Bold.woff2
farmdrop/static/fonts/Roboto-Light.eot
farmdrop/static/fonts/Roboto-Light.ttf
farmdrop/static/fonts/Roboto-Light.woff
farmdrop/static/fonts/Roboto-Light.woff2
farmdrop/static/fonts/Roboto-Medium.eot
farmdrop/static/fonts/Roboto-Medium.ttf
farmdrop/static/fonts/Roboto-Medium.woff
farmdrop/static/fonts/Roboto-Medium.woff2
farmdrop/static/fonts/Roboto-Regular.eot
farmdrop/static/fonts/Roboto-Regular.ttf
farmdrop/static/fonts/Roboto-Regular.woff
farmdrop/static/fonts/Roboto-Regular.woff2
farmdrop/static/fonts/Roboto-Thin.eot
farmdrop/static/fonts/Roboto-Thin.ttf
farmdrop/static/fonts/Roboto-Thin.woff
farmdrop/static/fonts/Roboto-Thin.woff2
farmdrop/static/fonts/fontawesome-webfont.eot
farmdrop/static/fonts/fontawesome-webfont.svg
farmdrop/static/fonts/fontawesome-webfont.ttf
farmdrop-0.2.0.dist-info/DESCRIPTION.rst
farmdrop-0.2.0.dist-info/METADATA
farmdrop-0.2.0.dist-info/RECORD
farmdrop-0.2.0.dist-info/WHEEL
farmdrop-0.2.0.dist-info/entry_points.txt
farmdrop-0.2.0.dist-info/metadata.json
farmdrop-0.2.0.dist-info/top_level.txt
