Metadata-Version: 2.0
Name: farmdrop
Version: 0.2.0
Summary: MLJtrust.org Django applications.
Home-page: http://gitlab.com/farmdrop/farmdrop
Author: Colin Powell
Author-email: colin.powell@fiveq.com
License: Closed
Platform: OS Independent
Classifier: Development Status :: 4 - Beta
Classifier: Framework :: Django
Classifier: Intended Audience :: Developers
Classifier: License :: OSI Approved :: BSD License
Classifier: Operating System :: OS Independent
Classifier: Programming Language :: Python
Classifier: Topic :: Internet :: WWW/HTTP
Classifier: Topic :: Internet :: WWW/HTTP :: Dynamic Content
Requires-Dist: Django (<1.10,>=1.9)
Requires-Dist: django-oscar (>=1.3)
Requires-Dist: django-configurations (>=2.0)
Requires-Dist: dj-database-url (>=0.3.0)
Requires-Dist: dj-haystack-url (>=0.2.0)
Requires-Dist: django-cache-url (>=0.8.0)
Requires-Dist: werkzeug (>=0.9.4)
Requires-Dist: Pillow (>=3)
Requires-Dist: unidecode (>=0.4.19)
Requires-Dist: whoosh (>=2.7.4)
Requires-Dist: gunicorn (>=0.19)
Requires-Dist: markdown (==2.6.1)
Requires-Dist: easy-thumbnails (>=1.2)
Requires-Dist: whitenoise (>=3.2)
Requires-Dist: google-measurement-protocol (>=0.1.6)
Requires-Dist: google-i18n-address (>=1.0.7)
Requires-Dist: jsonfield (>=1.0.3)
Requires-Dist: maxminddb-geolite2 (>=2015.708)
Requires-Dist: django-jenkins (>=0.18)
Requires-Dist: django-haystack (>=2.4)
Requires-Dist: django-debug-toolbar (>=1.4)
Requires-Dist: django-extensions (>=1.6.1)
Requires-Dist: django-braces (>=1.4.0)
Requires-Dist: django-localflavor (>=1.1)
Requires-Dist: django-allauth (>=0.24.1)
Requires-Dist: django-floppyforms (>=1.6.1)
Requires-Dist: django-custom-user (>=0.5)
Requires-Dist: django-nose (>=1.4.1)
Requires-Dist: django-smartcc (>=0.1.2)
Requires-Dist: djangorestframework (==3.3.2)
Requires-Dist: django-cors-headers (==1.1.0)
Requires-Dist: django-templated-email (>=0.4.9)
Requires-Dist: django-robots (==2.0)
Requires-Dist: django-typogrify (==1.3.3)
Requires-Dist: django-offsite-storage (>=0.0.10)
Requires-Dist: django-redis (>=4.4.3)
Requires-Dist: raven (>=5.2.0)
